[
    {
        "title": "RageTV",
        "url": "intro.mp4"
    },
    {
        "image": "https://image.tmdb.org/t/p/original/4yFG6cSPaCaPhyJ1vtGOtMD1lgh.jpg",
        "category": "Film Library",
        "title": "The Banshees of Inisherin (2022)",
        "url": "https://pkaystream.cc/pl/Ex108P8H7f/720?e="
    },
    {
        "title": "RageTV",
        "url": "intro.mp4"
    },
    {
        "image": "https://image.tmdb.org/t/p/original/iGoXIpQb7Pot00EEdwpwPajheZ5.jpg",
        "category": "Film Library",
        "title": "Harry Potter and the Deathly Hallows: Part 1 (2010)",
        "url": "https://pkaystream.cc/pl/RbDp4hO6Yl/720?e="
    },
    {
        "title": "RageTV",
        "url": "intro.mp4"
    },
    {
        "image": "https://image.tmdb.org/t/p/original/cgZjpqRQt9sk6XMCwZ3B1NPAaoy.jpg",
        "category": "Film Library",
        "title": "Hunting Grounds (2025)",
        "url": "https://pkaystream.cc/pl/FL65pAWzSM/720?e="
    },
    {
        "title": "RageTV",
        "url": "intro.mp4"
    },
    {
        "image": "https://image.tmdb.org/t/p/original/64ZktFMmTzsm47wdsaMOID0DzcY.jpg",
        "category": "Film Library",
        "title": "The Tiger's Apprentice (2024)",
        "url": "https://pkaystream.cc/pl/eOcnlB8Hbb/720?e="
    },
    {
        "title": "RageTV",
        "url": "intro.mp4"
    },
    {
        "image": "https://image.tmdb.org/t/p/original/gMT2ahTt0H6DF714pVCoVKwUOnB.jpg",
        "category": "Film Library",
        "title": "No Address (2025)",
        "url": "https://pkaystream.cc/pl/cJoyW5kFI4/720?e="
    }
]