[
    {
        "image": "https://image.tmdb.org/t/p/w500/rMm94JsRfcOPiPVsTRcBiiVBOhz.jpg",
        "category": "Movie Library",
        "title": "Ferdinand (2017)",
        "url": "http://scrennnifu.click/movie/tt3411444/playlist.m3u8"
    },
    {
        "image": "https://image.tmdb.org/t/p/w500/xbdRxyr1u5dbhvMm14w7J1jJWQS.jpg",
        "category": "Movie Library",
        "title": "O'Dessa (2025)",
        "url": "http://scrennnifu.click/movie/tt26304178/playlist.m3u8"
    },
    {
        "image": "https://image.tmdb.org/t/p/w500/jJCyIBPfvk41uETq6K6u4upyGO8.jpg",
        "category": "Movie Library",
        "title": "The Insider (1999)",
        "url": "http://scrennnifu.click/movie/tt0140352/playlist.m3u8"
    },
    {
        "image": "https://image.tmdb.org/t/p/w500/jBZeZZNjYBUU21zFvBnin5n62bv.jpg",
        "category": "Movie Library",
        "title": "Popstar: Never Stop Never Stopping (2016)",
        "url": "http://scrennnifu.click/movie/tt3960412/playlist.m3u8"
    },
    {
        "image": "https://image.tmdb.org/t/p/w500/ccn6bFUA5DECjA3Lo0CuJqGNQCv.jpg",
        "category": "Movie Library",
        "title": "One of Them Days (2025)",
        "url": "http://scrennnifu.click/movie/tt32221196/playlist.m3u8"
    },
    {
        "image": "https://image.tmdb.org/t/p/w500/xWlF2i51zUq7BUq4iJte1g9NyIM.jpg",
        "category": "Movie Library",
        "title": "Death of a Unicorn (2025)",
        "url": "http://scrennnifu.click/movie/tt28443655/playlist.m3u8"
    },
    {
        "image": "https://image.tmdb.org/t/p/w500/kziBJGQFo9f0Vkj9s37qI0G9I0I.jpg",
        "category": "Movie Library",
        "title": "Fire with Fire (2012)",
        "url": "http://scrennnifu.click/movie/tt1925431/playlist.m3u8"
    },
    {
        "image": "https://image.tmdb.org/t/p/w500/iIVcea2BHHi7RJgucGEmpt3zkED.jpg",
        "category": "Movie Library",
        "title": "The Whistleblower (2010)",
        "url": "http://scrennnifu.click/movie/tt0896872/playlist.m3u8"
    },
    {
        "image": "https://image.tmdb.org/t/p/w500/hHowAaChDjwueySmwVbsjHmpWa.jpg",
        "category": "Movie Library",
        "title": "High Rollers (2025)",
        "url": "http://scrennnifu.click/movie/tt27829510/playlist.m3u8"
    },
    {
        "image": "https://image.tmdb.org/t/p/w500/tzYJ9X9oVybCIVAaTOUFHVwcjXo.jpg",
        "category": "Movie Library",
        "title": "Locked Up (2017)",
        "url": "http://scrennnifu.click/movie/tt6772246/playlist.m3u8"
    },
    {
        "image": "https://image.tmdb.org/t/p/w500/2bDZl3PzFLFWe4gaFUQnnaslqT3.jpg",
        "category": "Movie Library",
        "title": "Just Mercy (2019)",
        "url": "http://scrennnifu.click/movie/tt4916630/playlist.m3u8"
    },
    {
        "image": "https://image.tmdb.org/t/p/w500/lbNemoc9bRIAIVck0e2cv1cgftN.jpg",
        "category": "Movie Library",
        "title": "Street Fighter: The Legend of Chun-Li (2009)",
        "url": "http://scrennnifu.click/movie/tt0891592/playlist.m3u8"
    },
    {
        "image": "",
        "category": "Movie Library",
        "title": "R. Kelly: A Faking It Special (0000)",
        "url": "http://scrennnifu.click/movie/tt21816348/playlist.m3u8"
    },
    {
        "image": "https://image.tmdb.org/t/p/w500/bJLCPROp9bmNndurwZpVnOioVpB.jpg",
        "category": "Movie Library",
        "title": "Zola (2021)",
        "url": "http://scrennnifu.click/movie/tt5439812/playlist.m3u8"
    },
    {
        "image": "https://image.tmdb.org/t/p/w500/rpz442GUtGvMwZY1sgf2gZZg91J.jpg",
        "category": "Movie Library",
        "title": "The Challenger Disaster (2019)",
        "url": "http://scrennnifu.click/movie/tt7783966/playlist.m3u8"
    }
]