[
    {
        "image": "https://image.tmdb.org/t/p/original/5ZEksAUM9z3XcvzzA5mO9POyxMx.jpg",
        "category": "Film Library",
        "title": "The Surfer (2025)",
        "url": "https://flashstream.cc/pl/VRoxPPgHhl/720?e="
    },
    {
        "image": "https://image.tmdb.org/t/p/original/n8ZpMwYT02XjpQHpSxn1eJw5Zpz.jpg",
        "category": "Film Library",
        "title": "Crater (2023)",
        "url": "https://flashstream.cc/pl/rE7xi9D_q3/720?e="
    },
    {
        "image": "https://image.tmdb.org/t/p/original/8c4a8kE7PizaGQQnditMmI1xbRp.jpg",
        "category": "Film Library",
        "title": "The Matrix Resurrections (2021)",
        "url": "https://flashstream.cc/pl/RIpI0RNrED/720?e="
    },
    {
        "image": "https://media.themoviedb.org/t/p/w220_and_h330_face/kXFHVJqZkWtkSRlLpv2clN8KP6E.jpg",
        "category": "Film Library",
        "title": "Anemone (2025)",
        "url": "https://flashstream.cc/pl/aBSiSbx-STXqJQh/0-0?e="
    },
    {
        "image": "https://image.tmdb.org/t/p/original/Akweo95FGyDpucYVT81h0SbX8Ky.jpg",
        "category": "Film Library",
        "title": "Brothers (2024)",
        "url": "https://flashstream.cc/pl/JLrDC5ShPs/720?e="
    }
]