[
    {
        "image": "https://image.tmdb.org/t/p/w600_and_h900_bestv2/b9n2R3xZWQ8MVZgndQoV34stS0h.jpg",
        "category": "Movie Library",
        "title": "Wrath of the Titans (2012)",
        "url": "http://tvnijuan.net:25461/movie/rictms/rictms/367.mp4"
    },
    {
        "image": "https://image.tmdb.org/t/p/w600_and_h900_bestv2/cvit6HDbXHE6W5kGPd47jd0wthQ.jpg",
        "category": "Movie Library",
        "title": "I Kill Giants (2017)",
        "url": "http://tvnijuan.net:25461/movie/rictms/rictms/91.mp4"
    },
    {
        "image": "https://image.tmdb.org/t/p/w600_and_h900_bestv2/hx0sdduAsr4rq03RZKZzglR25z7.jpg",
        "category": "Movie Library",
        "title": "Blade (1998)",
        "url": "http://tvnijuan.net:25461/movie/rictms/rictms/33.mp4"
    },
    {
        "image": "https://image.tmdb.org/t/p/w600_and_h900_bestv2/7sKiGNWFM15WNyY7LYd5vmb3brO.jpg",
        "category": "Movie Library",
        "title": "Texas Chainsaw Massacre (2022)",
        "url": "http://tvnijuan.net:25461/movie/rictms/rictms/1234.mp4"
    },
    {
        "image": "https://image.tmdb.org/t/p/w600_and_h900_bestv2/ylvfsnacoqsTdZuLty2XVRolnNH.jpg",
        "category": "Movie Library",
        "title": "Iron Eagle III (1992)",
        "url": "http://tvnijuan.net:25461/movie/rictms/rictms/547.mp4"
    },
    {
        "image": "https://image.tmdb.org/t/p/w600_and_h900_bestv2/sv1xJUazXeYqALzczSZ3O6nkH75.jpg",
        "category": "Movie Library",
        "title": "Black Panther: Wakanda Forever (2022)",
        "url": "http://tvnijuan.net:25461/movie/rictms/rictms/156.mp4"
    },
    {
        "image": "https://image.tmdb.org/t/p/w600_and_h900_bestv2/h6NYfVUyM6CDURtZSnBpz647Ldd.jpg",
        "category": "Movie Library",
        "title": "Fantastic Beasts and Where to Find Them (2016)",
        "url": "http://tvnijuan.net:25461/movie/rictms/rictms/865.mp4"
    },
    {
        "image": "https://image.tmdb.org/t/p/w600_and_h900_bestv2/4JyNWkryifWbWXJyxcWh3pVya6N.jpg",
        "category": "Movie Library",
        "title": "Purple Hearts (2022)",
        "url": "http://tvnijuan.net:25461/movie/rictms/rictms/1125.mp4"
    },
    {
        "image": "https://image.tmdb.org/t/p/w600_and_h900_bestv2/efwv6F2lGaghjPpBRSINHtoEiZB.jpg",
        "category": "Movie Library",
        "title": "Robot (2004)\" tvg-logo=\"https://image.tmdb.org/t/p/w600_and_h900_bestv2/efwv6F2lGaghjPpBRSINHtoEiZB.jpg\" group-title=\"VOD\",I, Robot (2004)",
        "url": "http://tvnijuan.net:25461/movie/rictms/rictms/840.mp4"
    },
    {
        "image": "https://image.tmdb.org/t/p/w600_and_h900_bestv2/v5gShop7147X33ytbcC2u05KDuc.jpg",
        "category": "Movie Library",
        "title": "Pride & Prejudice (2005)",
        "url": "http://tvnijuan.net:25461/movie/rictms/rictms/357.mp4"
    },
    {
        "image": "https://image.tmdb.org/t/p/w600_and_h900_bestv2/pmdgdb8biQLLzTjySZLPdK13KwM.jpg",
        "category": "Movie Library",
        "title": "Wanted Man (2024)",
        "url": "http://tvnijuan.net:25461/movie/rictms/rictms/324.mp4"
    },
    {
        "image": "https://image.tmdb.org/t/p/w600_and_h900_bestv2/yph9PAbmjYPvyvbeZvdYIhCZHEu.jpg",
        "category": "Movie Library",
        "title": "Bandit (2022)",
        "url": "http://tvnijuan.net:25461/movie/rictms/rictms/764.mp4"
    },
    {
        "image": "https://image.tmdb.org/t/p/w600_and_h900_bestv2/4tGMz5xUs9sk8X9B28G6UalHK1d.jpg",
        "category": "Movie Library",
        "title": "Young Adult (2011)",
        "url": "http://tvnijuan.net:25461/movie/rictms/rictms/1367.mp4"
    },
    {
        "image": "https://image.tmdb.org/t/p/w600_and_h900_bestv2/ripTQsmWQJyccK6zB1dajSY3olv.jpg",
        "category": "Movie Library",
        "title": "Mean Machine (2001)",
        "url": "http://tvnijuan.net:25461/movie/rictms/rictms/1067.mp4"
    },
    {
        "image": "https://image.tmdb.org/t/p/w600_and_h900_bestv2/dmn2nVo8h7LMnk694JxCRIwK06p.jpg",
        "category": "Movie Library",
        "title": "The Thing (2011)",
        "url": "http://tvnijuan.net:25461/movie/rictms/rictms/456.mp4"
    }
]