[
    {
        "title": "RageTV",
        "url": "intro.mp4"
    },
    {
        "image": "https://image.tmdb.org/t/p/original/wqfu3bPLJaEWJVk3QOm0rKhxf1A.jpg",
        "category": "Film Library",
        "title": "The Old Guard 2 (2025)",
        "url": "https://flashstream.cc/pl/nUSrijjGFV/720?e="
    },
    {
        "title": "RageTV",
        "url": "intro.mp4"
    },
    {
        "image": "https://image.tmdb.org/t/p/original/xBC7bHZ5UglTw4LMd2lTSgXvQXl.jpg",
        "category": "Film Library",
        "title": "Silent Hill: Revelation 3D (2012)",
        "url": "https://flashstream.cc/pl/iVJhnqFB1o/720?e="
    },
    {
        "title": "RageTV",
        "url": "intro.mp4"
    },
    {
        "image": "https://image.tmdb.org/t/p/original/qNBAXBIQlnOThrVvA6mA2B5ggV6.jpg",
        "category": "Film Library",
        "title": "The Super Mario Bros. Movie (2023)",
        "url": "https://flashstream.cc/pl/qJmLAfHRnU/720?e="
    },
    {
        "title": "RageTV",
        "url": "intro.mp4"
    },
    {
        "image": "https://media.themoviedb.org/t/p/w220_and_h330_face/uD5n48KdBXPa2e61dnGgmdVKcVg.jpg",
        "category": "Film Library",
        "title": "Fast & Furious (2009)",
        "url": "https://flashstream.cc/pl/68252IOdff81E64/1080?s=0&d=5&e="
    },
    {
        "title": "RageTV",
        "url": "intro.mp4"
    },
    {
        "image": "https://image.tmdb.org/t/p/original/wvpgvcWNkF2HLuTEMIM7K83MvZ.jpg",
        "category": "Film Library",
        "title": "Child's Play (1988)",
        "url": "https://flashstream.cc/pl/cwdxC4zCWT/720?e="
    }
]